[
	{ "s": "И", "p": [9, 2, 8, 17, 11, 12, 6, 18, 16, 15] },
	{ "s": "ИГР", "p": [17] },
	{ "s": "ИГРА", "p": [8, 15, 2, 17, 16, 11, 6, 5] },
	{ "s": "ИГРАТЬ", "p": [9] },
	{ "s": "ИГРЕ", "p": [17] },
	{ "s": "ИГРОВОГО", "p": [16] },
	{ "s": "ИГРОВОЙ", "p": [17] },
	{ "s": "ИГРОВЫЕ", "p": [5] },
	{ "s": "ИГРОК", "p": [17] },
	{ "s": "ИГРОКУ", "p": [5] },
	{ "s": "ИГРУ", "p": [17, 15, 5, 2] },
	{ "s": "ИГРЫ", "p": [9, 12, 7, 2] },
	{ "s": "ИЗМ", "p": [18] },
	{ "s": "ИЗМЕНЕН", "p": [18] },
	{ "s": "ИЗМЕНЕНИЙ", "p": [18] },
	{ "s": "ИЛИ", "p": [8, 13] },
	{ "s": "ИМ", "p": [9] },
	{ "s": "ИНЖЕНЕРИЯ", "p": [8] },
	{ "s": "ИНСТРУКЦИЮ", "p": [12] },
	{ "s": "ИНТЕРНЕТ", "p": [15] },
	{ "s": "ИНТЕРНЕТ-СОЕДИНЕНИЯ", "p": [15] },
	{ "s": "ИНФОРМАЦИОННОЙ", "p": [9, 8] },
	{ "s": "ИНФОРМАЦИЮ", "p": [2] },
	{ "s": "ИНФОРМАЦИЯ", "p": [2] },
	{ "s": "ИСПОЛНИТЕЛЕМ", "p": [8] },
	{ "s": "ИСПОЛНЯЕМЫЙ", "p": [8] },
	{ "s": "ИСПОЛЬЗОВАНИЯ", "p": [13, 7] },
	{ "s": "ИСПОЛЬЗУЕМЫМ", "p": [9] },
	{ "s": "ИСПОЛЬЗУЮЩИХ", "p": [5] },
	{ "s": "ИСПОЛЬЗУЯ", "p": [5] },
	{ "s": "ИСПЫТАНИЙ", "p": [8] },
	{ "s": "ИСХОДНЫЕ", "p": [9] },
	{ "s": "ИСХОДНЫМ", "p": [9] },
	{ "s": "ИХ", "p": [15, 5] }
]